{
  "placeholderImages": [
    {
      "id": "hero-earrings",
      "description": "Model wearing spectacular statement artificial earrings",
      "imageUrl": "https://picsum.photos/seed/earring-hero/1920/1080",
      "imageHint": "earring model"
    },
    {
      "id": "jhumka-green",
      "description": "Minakari Half Green Jhumka",
      "imageUrl": "https://picsum.photos/seed/green-jhumka/600/600",
      "imageHint": "green jhumka"
    },
    {
      "id": "jhumka-red",
      "description": "Minakari Half Red Jhumka",
      "imageUrl": "https://picsum.photos/seed/red-jhumka/600/600",
      "imageHint": "red jhumka"
    },
    {
      "id": "lotus-firozi",
      "description": "Lotus Minakari Firozi Drop Earrings",
      "imageUrl": "https://picsum.photos/seed/firozi-lotus/600/600",
      "imageHint": "firozi earrings"
    },
    {
      "id": "lotus-black",
      "description": "Lotus Minakari Black Drop Earrings",
      "imageUrl": "https://picsum.photos/seed/black-lotus/600/600",
      "imageHint": "black earrings"
    },
    {
      "id": "lotus-wine",
      "description": "Lotus Minakari Wine Drop Earrings",
      "imageUrl": "https://picsum.photos/seed/wine-lotus/600/600",
      "imageHint": "wine earrings"
    },
    {
      "id": "kundan-green",
      "description": "Green Crystal Kundan Drops Earring",
      "imageUrl": "https://picsum.photos/seed/green-kundan/600/600",
      "imageHint": "kundan earring"
    },
    {
      "id": "rect-gold",
      "description": "Gold Plated Rectangular Drop Earrings",
      "imageUrl": "https://picsum.photos/seed/rect-gold/600/600",
      "imageHint": "gold earrings"
    },
    {
      "id": "rect-mirror",
      "description": "Rectangular Drop Mirror Rose Gold Plated",
      "imageUrl": "https://picsum.photos/seed/mirror-rose/600/600",
      "imageHint": "mirror earrings"
    },
    {
      "id": "lifestyle-earring",
      "description": "Jewelry box filled with various earring styles",
      "imageUrl": "https://picsum.photos/seed/box1/800/800",
      "imageHint": "jewelry collection"
    },
    {
      "id": "lifestyle-1",
      "description": "Brand story lifestyle image",
      "imageUrl": "https://picsum.photos/seed/lifestyle1/800/1000",
      "imageHint": "jewelry lifestyle"
    },
    {
      "id": "ring-1",
      "description": "Luxury ring detail",
      "imageUrl": "https://picsum.photos/seed/ring1/400/400",
      "imageHint": "luxury ring"
    },
    {
      "id": "insta-1",
      "description": "Instagram feature 1",
      "imageUrl": "https://picsum.photos/seed/insta1/600/600",
      "imageHint": "fashion aesthetic"
    },
    {
      "id": "insta-2",
      "description": "Instagram feature 2",
      "imageUrl": "https://picsum.photos/seed/insta2/600/600",
      "imageHint": "jewelry detail"
    },
    {
      "id": "insta-3",
      "description": "Instagram feature 3",
      "imageUrl": "https://picsum.photos/seed/insta3/600/600",
      "imageHint": "luxury jewelry"
    },
    {
      "id": "insta-4",
      "description": "Instagram feature 4",
      "imageUrl": "https://picsum.photos/seed/insta4/600/600",
      "imageHint": "aesthetic vibe"
    }
  ]
}